{
  "project_info": {
    "project_number": "182647509460",
    "firebase_url": "https://fir-example-1c344.firebaseio.com",
    "project_id": "fir-example-1c344",
    "storage_bucket": "fir-example-1c344.appspot.com"
  },
  "client": [
    {
      "client_info": {
        "mobilesdk_app_id": "1:182647509460:android:a8b13fa014463dd27bc641",
        "android_client_info": {
          "package_name": "com.example.firebase"
        }
      },
      "oauth_client": [
        {
          "client_id": "182647509460-v43f9t0256i1ui2o30m140fc3f6lq3g6.apps.googleusercontent.com",
          "client_type": 3
        }
      ],
      "api_key": [
        {
          "current_key": "AIzaSyAz8Euz5-NLW20gMu63o7P6C8mQEBYuHjc"
        }
      ],
      "services": {
        "appinvite_service": {
          "other_platform_oauth_client": [
            {
              "client_id": "182647509460-v43f9t0256i1ui2o30m140fc3f6lq3g6.apps.googleusercontent.com",
              "client_type": 3
            }
          ]
        }
      }
    },
    {
      "client_info": {
        "mobilesdk_app_id": "1:182647509460:android:8f49b2787f7b9aec7bc641",
        "android_client_info": {
          "package_name": "com.example.firebasepushnotification"
        }
      },
      "oauth_client": [
        {
          "client_id": "182647509460-v43f9t0256i1ui2o30m140fc3f6lq3g6.apps.googleusercontent.com",
          "client_type": 3
        }
      ],
      "api_key": [
        {
          "current_key": "AIzaSyAz8Euz5-NLW20gMu63o7P6C8mQEBYuHjc"
        }
      ],
      "services": {
        "appinvite_service": {
          "other_platform_oauth_client": [
            {
              "client_id": "182647509460-v43f9t0256i1ui2o30m140fc3f6lq3g6.apps.googleusercontent.com",
              "client_type": 3
            }
          ]
        }
      }
    },
    {
      "client_info": {
        "mobilesdk_app_id": "1:182647509460:android:0bb56983a1b79f7f7bc641",
        "android_client_info": {
          "package_name": "com.example.groupchat"
        }
      },
      "oauth_client": [
        {
          "client_id": "182647509460-v43f9t0256i1ui2o30m140fc3f6lq3g6.apps.googleusercontent.com",
          "client_type": 3
        }
      ],
      "api_key": [
        {
          "current_key": "AIzaSyAz8Euz5-NLW20gMu63o7P6C8mQEBYuHjc"
        }
      ],
      "services": {
        "appinvite_service": {
          "other_platform_oauth_client": [
            {
              "client_id": "182647509460-v43f9t0256i1ui2o30m140fc3f6lq3g6.apps.googleusercontent.com",
              "client_type": 3
            }
          ]
        }
      }
    },
    {
      "client_info": {
        "mobilesdk_app_id": "1:182647509460:android:6b1843960d135c2f7bc641",
        "android_client_info": {
          "package_name": "com.example.groupchatapp"
        }
      },
      "oauth_client": [
        {
          "client_id": "182647509460-v43f9t0256i1ui2o30m140fc3f6lq3g6.apps.googleusercontent.com",
          "client_type": 3
        }
      ],
      "api_key": [
        {
          "current_key": "AIzaSyAz8Euz5-NLW20gMu63o7P6C8mQEBYuHjc"
        }
      ],
      "services": {
        "appinvite_service": {
          "other_platform_oauth_client": [
            {
              "client_id": "182647509460-v43f9t0256i1ui2o30m140fc3f6lq3g6.apps.googleusercontent.com",
              "client_type": 3
            }
          ]
        }
      }
    }
  ],
  "configuration_version": "1"
}